zoneminder/__init__.py
zoneminder/exceptions.py
zoneminder/monitor.py
zoneminder/run_state.py
zoneminder/zm.py
zm_py-0.5.3.dist-info/LICENSE.md
zm_py-0.5.3.dist-info/METADATA
zm_py-0.5.3.dist-info/WHEEL
zm_py-0.5.3.dist-info/RECORD
