Metadata-Version: 2.1
Name: zm-py
Version: 0.5.3
Summary: A loose python wrapper around the ZoneMinder REST API.
Home-page: https://github.com/rohankapoorcom/zm-py
License: Apache-2.0
Author: Rohan Kapoor
Author-email: rohan@rohankapoor.com
Maintainer: Nic Boet
Maintainer-email: nic@boet.cc
Requires-Python: >=3.11,<4.0
Classifier: Intended Audience :: Developers
Classifier: License :: OSI Approved :: Apache Software License
Classifier: Operating System :: OS Independent
Classifier: Programming Language :: Python
Classifier: Programming Language :: Python :: 3
Classifier: Programming Language :: Python :: 3.11
Classifier: Programming Language :: Python :: 3.12
Classifier: Topic :: Home Automation
Classifier: Topic :: Software Development :: Libraries :: Python Modules
Requires-Dist: requests (>=2.0)
Project-URL: Repository, https://github.com/rohankapoorcom/zm-py
